pyspectre/Analyses.py
pyspectre/Pyspectre.py
pyspectre/__init__.py
pyspectre/server.py
pyspectre/parallel/Pyspectre_parallel.py
pyspectre/parallel/__init__.py
pyspectre/parallel/replwrap_parallel.py
pyspectre/spectre/__init__.py
pyspectre/spectre/replwrap_server.py
pyspectre/spectre/skill_cmd.py
pyspectre/spectre/skill_interface.py
pyspectre/tests/__init__.py
pyspectre/tests/testscript.py
pyspectre-0.2b5.dist-info/LICENSE
pyspectre-0.2b5.dist-info/METADATA
pyspectre-0.2b5.dist-info/WHEEL
pyspectre-0.2b5.dist-info/entry_points.txt
pyspectre-0.2b5.dist-info/top_level.txt
pyspectre-0.2b5.dist-info/RECORD
