Metadata-Version: 2.1
Name: pyspectre
Version: 0.2b5
Summary: python interface to supervise and control single instance of Spectre circuit simulator
Home-page: http://github.gatech.edu/lars/pyspectre
Author: Barry Muldrey
Author-email: bmuldrey3@gatech.edu
License: MIT
Platform: UNKNOWN
Requires-Dist: pexpect
Requires-Dist: numpy
Requires-Dist: libpsf
Provides-Extra: server
Requires-Dist: waverunner ; extra == 'server'
Requires-Dist: xarray ; extra == 'server'
Requires-Dist: scipy ; extra == 'server'
